gepa_dapo_grn/__init__.py
gepa_dapo_grn/_compat.py
gepa_dapo_grn/_ema_helpers.py
gepa_dapo_grn/_version.py
gepa_dapo_grn/config.py
gepa_dapo_grn/curriculum.py
gepa_dapo_grn/dapo_core.py
gepa_dapo_grn/eval_hooks.py
gepa_dapo_grn/gepa_interfaces.py
gepa_dapo_grn/grn.py
gepa_dapo_grn/logging_utils.py
gepa_dapo_grn/policy_interfaces.py
gepa_dapo_grn/reward_mixers.py
gepa_dapo_grn/safety_controller.py
gepa_dapo_grn/integration/__init__.py
gepa_dapo_grn/integration/hf_lm.py
gepa_dapo_grn-0.1.0.dist-info/licenses/LICENSE
gepa_dapo_grn-0.1.0.dist-info/METADATA
gepa_dapo_grn-0.1.0.dist-info/WHEEL
gepa_dapo_grn-0.1.0.dist-info/top_level.txt
gepa_dapo_grn-0.1.0.dist-info/RECORD
