Metadata-Version: 2.4
Name: gepa-dapo-grn
Version: 0.1.0
Summary: GEPA-aware DAPO reinforcement learning with optional Global Response Normalization
Author: InfiniteMalice
License: MIT
Project-URL: Homepage, https://github.com/InfiniteMalice/gepa-dapo-grn
Project-URL: Repository, https://github.com/InfiniteMalice/gepa-dapo-grn
Project-URL: Issues, https://github.com/InfiniteMalice/gepa-dapo-grn/issues
Classifier: Development Status :: 3 - Alpha
Classifier: Intended Audience :: Science/Research
Classifier: License :: OSI Approved :: MIT License
Classifier: Programming Language :: Python :: 3
Classifier: Programming Language :: Python :: 3.9
Classifier: Programming Language :: Python :: 3.10
Classifier: Programming Language :: Python :: 3.11
Classifier: Programming Language :: Python :: 3.12
Classifier: Topic :: Scientific/Engineering :: Artificial Intelligence
Requires-Python: >=3.9
License-File: LICENSE
Requires-Dist: torch<3.0,>=2.0
Provides-Extra: hf
Requires-Dist: transformers<5.0,>=4.40; extra == "hf"
Provides-Extra: dev
Requires-Dist: pytest; extra == "dev"
Requires-Dist: ruff; extra == "dev"
Requires-Dist: black; extra == "dev"
Dynamic: license-file
